MANIFEST.in
README.md
README.rst
setup.py
qsuite/__init__.py
qsuite/printparams.py
qsuite/qconfig.py
qsuite/qsuite_binary.py
qsuite/qsuiteparse.py
qsuite/ssh.py
qsuite/submitjob.py
qsuite/template.py
qsuite/tools.py
qsuite.egg-info/PKG-INFO
qsuite.egg-info/SOURCES.txt
qsuite.egg-info/dependency_links.txt
qsuite.egg-info/entry_points.txt
qsuite.egg-info/not-zip-safe
qsuite.egg-info/requires.txt
qsuite.egg-info/top_level.txt
qsuite/jobscripts/PBSdummy.sh
qsuite/jobscripts/SGEdummy.sh
qsuite/queuesys/__init__.py
qsuite/queuesys/__init__.pyc
qsuite/queuesys/job.py
qsuite/queuesys/job.pyc
qsuite/queuesys/wrap_results.py
qsuite/queuesys/wrap_results.pyc
qsuite/templates/custom_wrap_results.py
qsuite/templates/qsuite_config.py
qsuite/templates/simulation.py
test/test.py
test/testmodule_.py