Metadata-Version: 1.0
Name: qsuite
Version: 0.4.14
Summary: A CLI to submit and retrieve large-scale jobs/results to and from HPC clusters.
Home-page: https://github.com/benmaier/qsuite
Author: Benjamin F. Maier
Author-email: benjaminfrankmaier@gmail.com
License: MIT
Platform: UNKNOWN
